py3xui/__init__.py
py3xui/api/__init__.py
py3xui/api/api.py
py3xui/api/api_base.py
py3xui/api/api_client.py
py3xui/api/api_database.py
py3xui/api/api_inbound.py
py3xui/api/api_server.py
py3xui/async_api/__init__.py
py3xui/async_api/async_api.py
py3xui/async_api/async_api_base.py
py3xui/async_api/async_api_client.py
py3xui/async_api/async_api_database.py
py3xui/async_api/async_api_inbound.py
py3xui/async_api/async_api_server.py
py3xui/client/__init__.py
py3xui/client/client.py
py3xui/inbound/__init__.py
py3xui/inbound/bases.py
py3xui/inbound/inbound.py
py3xui/inbound/settings.py
py3xui/inbound/sniffing.py
py3xui/inbound/stream_settings.py
py3xui/server/__init__.py
py3xui/server/server.py
py3xui/utils/__init__.py
py3xui/utils/env.py
py3xui-0.5.5.dist-info/licenses/LICENSE.md
py3xui-0.5.5.dist-info/METADATA
py3xui-0.5.5.dist-info/WHEEL
py3xui-0.5.5.dist-info/top_level.txt
py3xui-0.5.5.dist-info/RECORD
