Metadata-Version: 2.4
Name: py3xui
Version: 0.5.5
Summary: Sync and Async Object-oriented Python SDK for the 3x-ui app.
Author-email: iwatkot <iwatkot@gmail.com>
License: MIT License
Project-URL: Homepage, https://github.com/iwatkot/py3xui
Project-URL: Repository, https://github.com/iwatkot/py3xui
Keywords: vpn,3x-ui,sdk,api
Classifier: Programming Language :: Python :: 3.11
Classifier: Programming Language :: Python :: 3.12
Classifier: License :: OSI Approved :: MIT License
Classifier: Operating System :: OS Independent
License-File: LICENSE.md
Requires-Dist: pydantic>=2.0.0
Requires-Dist: requests>=2.0.0
Requires-Dist: httpx>=0.20.0
Dynamic: license-file
